hurry.workflow-4.0-py3.11-nspkg.pth
hurry/workflow/__init__.py
hurry/workflow/configure.zcml
hurry/workflow/interfaces.py
hurry/workflow/workflow.py
hurry/workflow/workflow.txt
hurry/workflow/tests/__init__.py
hurry/workflow/tests/test_doctest.py
hurry/workflow/tests/test_edgecases.py
hurry/workflow/tests/test_ordering.py
hurry.workflow-4.0.dist-info/LICENSE.txt
hurry.workflow-4.0.dist-info/METADATA
hurry.workflow-4.0.dist-info/WHEEL
hurry.workflow-4.0.dist-info/namespace_packages.txt
hurry.workflow-4.0.dist-info/top_level.txt
hurry.workflow-4.0.dist-info/RECORD
