Metadata-Version: 2.1
Name: hurry.workflow
Version: 4.0
Summary: hurry.workflow is a simple workflow system. It can be used to implement stateful multi-version workflows for Zope Toolkit applications.
Author: Martijn Faassen (at Infrae)
Author-email: faassen@startifact.com
License: ZPL2.1
Keywords: zope zope3
Classifier: Environment :: Web Environment
Classifier: Intended Audience :: Developers
Classifier: License :: OSI Approved :: Zope Public License
Classifier: Programming Language :: Python
Classifier: Programming Language :: Python :: 3
Classifier: Programming Language :: Python :: 3.7
Classifier: Programming Language :: Python :: 3.8
Classifier: Programming Language :: Python :: 3.9
Classifier: Programming Language :: Python :: 3.10
Classifier: Programming Language :: Python :: 3.11
Classifier: Programming Language :: Python :: Implementation
Classifier: Programming Language :: Python :: Implementation :: CPython
Classifier: Programming Language :: Python :: Implementation :: PyPy
Classifier: Framework :: Zope :: 3
Requires-Python: >=3.7
License-File: LICENSE.txt
Requires-Dist: setuptools
Requires-Dist: zope.interface
Requires-Dist: zope.component
Requires-Dist: zope.event
Requires-Dist: zope.security
Requires-Dist: zope.annotation
Requires-Dist: zope.lifecycleevent
Provides-Extra: test
